easymongo/__init__.py
easymongo/easymongo.py
easymongo/errors.py
easymongo-1.215.0.dist-info/LICENSE
easymongo-1.215.0.dist-info/METADATA
easymongo-1.215.0.dist-info/WHEEL
easymongo-1.215.0.dist-info/top_level.txt
easymongo-1.215.0.dist-info/RECORD
