Metadata-Version: 2.1
Name: easymongo
Version: 1.215.0
Summary: Work easier with MongoDB in Python
Home-page: https://github.com/catenae/easymongo
Author: Rodrigo Martínez Castaño
Author-email: rodrigo@martinez.gal
License: GNU General Public License v3 (GPLv3)
Platform: UNKNOWN
Classifier: Development Status :: 4 - Beta
Classifier: Environment :: Console
Classifier: Intended Audience :: Developers
Classifier: License :: OSI Approved :: GNU General Public License v3 (GPLv3)
Classifier: Operating System :: POSIX :: Linux
Classifier: Programming Language :: Python :: 3.6
Classifier: Programming Language :: Python :: Implementation :: PyPy
Classifier: Topic :: Software Development :: Libraries :: Python Modules
Requires-Dist: pymongo (<4.0.0,>=3.9.0)
Requires-Dist: dnspython (<3.0.0,>=2.1.0)
